zebende/__init__.py
zebende/array_to_c_pointer_convert.py
zebende/dcca.py
zebende/dcca_of_from_dmcx2_of.py
zebende/detrended_series.py
zebende/dfa.py
zebende/dfa_pure_python.py
zebende/dmc_of_all_as_y.py
zebende/dmcx2.py
zebende/dmcx2_from_p_dcca_matrix.py
zebende/dmcx2_pure_python.py
zebende/get_platform.py
zebende/integrated_series.py
zebende/mat_index_comb.py
zebende/ordering_x_dmcx2_of.py
zebende/p_dcca.py
zebende/p_dcca_matrix_output.py
zebende/p_dcca_matrix_to_simple.py
zebende/p_dcca_pure_python.py
zebende/p_dcca_simple_output.py
zebende/p_dcca_simple_to_matrix.py
zebende/print_pdcca_matrix_by_level.py
zebende/time_windows.py
zebende/zig_libs/aarch64-linux/libzebendezig.so
zebende/zig_libs/aarch64-macos/libzebendezig.dylib
zebende/zig_libs/aarch64-windows/zebendezig.dll
zebende/zig_libs/x86_64-linux/libzebendezig.so
zebende/zig_libs/x86_64-macos/libzebendezig.dylib
zebende/zig_libs/x86_64-windows/zebendezig.dll
zebende-0.2.2.dist-info/METADATA
zebende-0.2.2.dist-info/WHEEL
zebende-0.2.2.dist-info/RECORD
